spotify_refresh_token_generator/__init__.py
spotify_refresh_token_generator/__main__.py
spotify_refresh_token_generator-0.0.10.dist-info/LICENSE
spotify_refresh_token_generator-0.0.10.dist-info/METADATA
spotify_refresh_token_generator-0.0.10.dist-info/WHEEL
spotify_refresh_token_generator-0.0.10.dist-info/entry_points.txt
spotify_refresh_token_generator-0.0.10.dist-info/top_level.txt
spotify_refresh_token_generator-0.0.10.dist-info/RECORD
